{
  "icons_by_filename": {
    "eslint.config.cjs": {
      "name": "Eslintrc",
      "cterm_color": "56",
      "color": "#4B32C3",
      "icon": ""
    },
    "hyprlandd.conf": {
      "name": "Hyprlandd",
      "cterm_color": "37",
      "color": "#00AAAE",
      "icon": ""
    },
    "settings.gradle": {
      "name": "GradleSettings",
      "cterm_color": "24",
      "color": "#005F87",
      "icon": ""
    },
    "PrusaSlicerGcodeViewer.ini": {
      "name": "PrusaSlicer",
      "cterm_color": "202",
      "color": "#EC6B23",
      "icon": ""
    },
    ".nvmrc": {
      "name": "node",
      "cterm_color": "71",
      "color": "#5FA04E",
      "icon": ""
    },
    ".gitmodules": {
      "name": "GitModules",
      "cterm_color": "196",
      "color": "#F54D27",
      "icon": ""
    },
    "tailwind.config.ts": {
      "name": "TailwindConfig",
      "cterm_color": "45",
      "color": "#20C2E3",
      "icon": "󱏿"
    },
    "bun.lockb": {
      "name": "BunLockfile",
      "cterm_color": "253",
      "color": "#EADCD1",
      "icon": ""
    },
    ".npmignore": {
      "name": "NPMIgnore",
      "cterm_color": "197",
      "color": "#E8274B",
      "icon": ""
    },
    "wrangler.jsonc": {
      "name": "WranglerConfig",
      "cterm_color": "208",
      "color": "#F48120",
      "icon": ""
    },
    ".prettierrc.toml": {
      "name": "PrettierConfig",
      "cterm_color": "33",
      "color": "#4285F4",
      "icon": ""
    },
    ".zshenv": {
      "name": "Zshenv",
      "cterm_color": "113",
      "color": "#89E051",
      "icon": ""
    },
    "code_of_conduct": {
      "name": "CodeOfConduct",
      "cterm_color": "161",
      "color": "#E41662",
      "icon": ""
    },
    ".Xauthority": {
      "name": "Xauthority",
      "cterm_color": "196",
      "color": "#E54D18",
      "icon": ""
    },
    "gradle-wrapper.properties": {
      "name": "GradleWrapperProperties",
      "cterm_color": "24",
      "color": "#005F87",
      "icon": ""
    },
    ".clang-tidy": {
      "name": "ClangConfig",
      "cterm_color": "66",
      "color": "#6D8086",
      "icon": ""
    },
    ".prettierrc.cjs": {
      "name": "PrettierConfig",
      "cterm_color": "33",
      "color": "#4285F4",
      "icon": ""
    },
    ".clangd": {
      "name": "ClangConfig",
      "cterm_color": "66",
      "color": "#6D8086",
      "icon": ""
    },
    "playwright.config.js": {
      "name": "PlaywrightConfig",
      "cterm_color": "34",
      "color": "#2FAD33",
      "icon": ""
    },
    ".Xresources": {
      "name": "Xresources",
      "cterm_color": "196",
      "color": "#E54D18",
      "icon": ""
    },
    "weston.ini": {
      "name": "Weston",
      "cterm_color": "214",
      "color": "#FFBB01",
      "icon": ""
    },
    "vite.config.mts": {
      "name": "ViteConfig",
      "cterm_color": "214",
      "color": "#FFA800",
      "icon": ""
    },
    "vercel.json": {
      "name": "Vercel",
      "cterm_color": "231",
      "color": "#FFFFFF",
      "icon": ""
    },
    "docker-compose.yaml": {
      "name": "Dockerfile",
      "cterm_color": "68",
      "color": "#458EE6",
      "icon": "󰡨"
    },
    "compose.yaml": {
      "name": "Dockerfile",
      "cterm_color": "68",
      "color": "#458EE6",
      "icon": "󰡨"
    },
    "build": {
      "name": "BazelBuild",
      "cterm_color": "113",
      "color": "#89E051",
      "icon": ""
    },
    ".luaurc": {
      "name": "Luaurc",
      "cterm_color": "75",
      "color": "#00A2FF",
      "icon": ""
    },
    "AUTHORS.txt": {
      "name": "AUTHORS",
      "cterm_color": "135",
      "color": "#A172FF",
      "icon": ""
    },
    "pnpm-lock.yaml": {
      "name": "PNPMLock",
      "cterm_color": "214",
      "color": "#F9AD02",
      "icon": ""
    },
    ".codespellrc": {
      "name": "Codespell",
      "cterm_color": "41",
      "color": "#35DA60",
      "icon": "󰓆"
    },
    "mix.lock": {
      "name": "MixLock",
      "cterm_color": "140",
      "color": "#A074C4",
      "icon": ""
    },
    "hyprlock.conf": {
      "name": "Hyprlock",
      "cterm_color": "37",
      "color": "#00AAAE",
      "icon": ""
    },
    "bspwmrc": {
      "name": "BSPWM",
      "cterm_color": "236",
      "color": "#2F2F2F",
      "icon": ""
    },
    ".prettierrc.json5": {
      "name": "PrettierConfig",
      "cterm_color": "33",
      "color": "#4285F4",
      "icon": ""
    },
    "license.md": {
      "name": "License",
      "cterm_color": "185",
      "color": "#D0BF41",
      "icon": ""
    },
    ".prettierignore": {
      "name": "PrettierIgnore",
      "cterm_color": "33",
      "color": "#4285F4",
      "icon": ""
    },
    "fp-info-cache": {
      "name": "KiCadCache",
      "cterm_color": "231",
      "color": "#FFFFFF",
      "icon": ""
    },
    "kdeglobals": {
      "name": "KDEglobals",
      "cterm_color": "32",
      "color": "#1C99F3",
      "icon": ""
    },
    ".zshrc": {
      "name": "Zshrc",
      "cterm_color": "113",
      "color": "#89E051",
      "icon": ""
    },
    "webpack": {
      "name": "Webpack",
      "cterm_color": "74",
      "color": "#519ABA",
      "icon": "󰜫"
    },
    "checkhealth": {
      "name": "Checkhealth",
      "cterm_color": "75",
      "color": "#75B4FB",
      "icon": "󰓙"
    },
    ".npmrc": {
      "name": "NPMrc",
      "cterm_color": "197",
      "color": "#E8274B",
      "icon": ""
    },
    "PKGBUILD": {
      "name": "PKGBUILD",
      "cterm_color": "67",
      "color": "#0F94D2",
      "icon": ""
    },
    ".prettierrc.yml": {
      "name": "PrettierConfig",
      "cterm_color": "33",
      "color": "#4285F4",
      "icon": ""
    },
    "commit_editmsg": {
      "name": "GitCommit",
      "cterm_color": "196",
      "color": "#F54D27",
      "icon": ""
    },
    ".gitattributes": {
      "name": "GitAttributes",
      "cterm_color": "196",
      "color": "#F54D27",
      "icon": ""
    },
    ".vimrc": {
      "name": "Vimrc",
      "cterm_color": "28",
      "color": "#019833",
      "icon": ""
    },
    "xsettingsd.conf": {
      "name": "XSettingsdConf",
      "cterm_color": "196",
      "color": "#E54D18",
      "icon": ""
    },
    "gruntfile.babel.js": {
      "name": "Gruntfile",
      "cterm_color": "166",
      "color": "#E37933",
      "icon": ""
    },
    "xorg.conf": {
      "name": "XorgConf",
      "cterm_color": "196",
      "color": "#E54D18",
      "icon": ""
    },
    "xmonad.hs": {
      "name": "xmonad",
      "cterm_color": "203",
      "color": "#FD4D5D",
      "icon": ""
    },
    "xmobarrc.hs": {
      "name": "xmonad",
      "cterm_color": "203",
      "color": "#FD4D5D",
      "icon": ""
    },
    "rakefile": {
      "name": "Rakefile",
      "cterm_color": "52",
      "color": "#701516",
      "icon": ""
    },
    "vite.config.mjs": {
      "name": "ViteConfig",
      "cterm_color": "214",
      "color": "#FFA800",
      "icon": ""
    },
    "xdph.conf": {
      "name": "XDPH",
      "cterm_color": "37",
      "color": "#00AAAE",
      "icon": ""
    },
    "wrangler.toml": {
      "name": "WranglerConfig",
      "cterm_color": "208",
      "color": "#F48120",
      "icon": ""
    },
    ".babelrc": {
      "name": "Babelrc",
      "cterm_color": "185",
      "color": "#CBCB41",
      "icon": ""
    },
    "AUTHORS": {
      "name": "AUTHORS",
      "cterm_color": "135",
      "color": "#A172FF",
      "icon": ""
    },
    "lxde-rc.xml": {
      "name": "LXDEConfigFile",
      "cterm_color": "246",
      "color": "#909090",
      "icon": ""
    },
    "vlcrc": {
      "name": "VLC",
      "cterm_color": "208",
      "color": "#EE7A00",
      "icon": "󰕼"
    },
    "vitest.config.ts": {
      "name": "VitestConfig",
      "cterm_color": "106",
      "color": "#739B1B",
      "icon": ""
    },
    "prisma.config.mts": {
      "name": "PrismaConfig",
      "cterm_color": "62",
      "color": "#5A67D8",
      "icon": ""
    },
    "vitest.config.mts": {
      "name": "VitestConfig",
      "cterm_color": "106",
      "color": "#739B1B",
      "icon": ""
    },
    ".env": {
      "name": "Env",
      "cterm_color": "227",
      "color": "#FAF743",
      "icon": ""
    },
    "vitest.config.mjs": {
      "name": "VitestConfig",
      "cterm_color": "106",
      "color": "#739B1B",
      "icon": ""
    },
    ".condarc": {
      "name": "Conda",
      "cterm_color": "34",
      "color": "#43B02A",
      "icon": ""
    },
    ".pre-commit-config.yaml": {
      "name": "PreCommitConfig",
      "cterm_color": "214",
      "color": "#F8B424",
      "icon": "󰛢"
    },
    "_vimrc": {
      "name": "Vimrc",
      "cterm_color": "28",
      "color": "#019833",
      "icon": ""
    },
    "vitest.config.cts": {
      "name": "VitestConfig",
      "cterm_color": "106",
      "color": "#739B1B",
      "icon": ""
    },
    "vitest.config.cjs": {
      "name": "VitestConfig",
      "cterm_color": "106",
      "color": "#739B1B",
      "icon": ""
    },
    "PrusaSlicer.ini": {
      "name": "PrusaSlicer",
      "cterm_color": "202",
      "color": "#EC6B23",
      "icon": ""
    },
    "vite.config.ts": {
      "name": "ViteConfig",
      "cterm_color": "214",
      "color": "#FFA800",
      "icon": ""
    },
    "xmobarrc": {
      "name": "xmonad",
      "cterm_color": "203",
      "color": "#FD4D5D",
      "icon": ""
    },
    ".editorconfig": {
      "name": "EditorConfig",
      "cterm_color": "255",
      "color": "#FFF2F2",
      "icon": ""
    },
    ".xinitrc": {
      "name": "XInitrc",
      "cterm_color": "196",
      "color": "#E54D18",
      "icon": ""
    },
    "vite.config.cts": {
      "name": "ViteConfig",
      "cterm_color": "214",
      "color": "#FFA800",
      "icon": ""
    },
    "prettier.config.mjs": {
      "name": "PrettierConfig",
      "cterm_color": "33",
      "color": "#4285F4",
      "icon": ""
    },
    "vite.config.cjs": {
      "name": "ViteConfig",
      "cterm_color": "214",
      "color": "#FFA800",
      "icon": ""
    },
    "ext_typoscript_setup.txt": {
      "name": "TypoScriptSetup",
      "cterm_color": "208",
      "color": "#FF8700",
      "icon": ""
    },
    ".prettierrc": {
      "name": "PrettierConfig",
      "cterm_color": "33",
      "color": "#4285F4",
      "icon": ""
    },
    "hypridle.conf": {
      "name": "Hypridle",
      "cterm_color": "37",
      "color": "#00AAAE",
      "icon": ""
    },
    "containerfile": {
      "name": "Dockerfile",
      "cterm_color": "68",
      "color": "#458EE6",
      "icon": "󰡨"
    },
    "vagrantfile": {
      "name": "Vagrantfile",
      "cterm_color": "27",
      "color": "#1563FF",
      "icon": ""
    },
    ".gitlab-ci.yml": {
      "name": "GitlabCI",
      "cterm_color": "196",
      "color": "#E24329",
      "icon": ""
    },
    ".gtkrc-2.0": {
      "name": "GTK",
      "cterm_color": "231",
      "color": "#FFFFFF",
      "icon": ""
    },
    "unlicense": {
      "name": "License",
      "cterm_color": "185",
      "color": "#D0BF41",
      "icon": ""
    },
    "tsconfig.json": {
      "name": "TSConfig",
      "cterm_color": "74",
      "color": "#519ABA",
      "icon": ""
    },
    "tmux.conf.local": {
      "name": "Tmux",
      "cterm_color": "34",
      "color": "#14BA19",
      "icon": ""
    },
    "justfile": {
      "name": "Justfile",
      "cterm_color": "66",
      "color": "#6D8086",
      "icon": ""
    },
    "readme.md": {
      "name": "Readme",
      "cterm_color": "255",
      "color": "#EDEDED",
      "icon": "󰂺"
    },
    "tailwind.config.js": {
      "name": "TailwindConfig",
      "cterm_color": "45",
      "color": "#20C2E3",
      "icon": "󱏿"
    },
    "license": {
      "name": "License",
      "cterm_color": "185",
      "color": "#D0BF41",
      "icon": ""
    },
    "sym-lib-table": {
      "name": "KiCadSymbolTable",
      "cterm_color": "231",
      "color": "#FFFFFF",
      "icon": ""
    },
    "sxhkdrc": {
      "name": "BSPWM",
      "cterm_color": "236",
      "color": "#2F2F2F",
      "icon": ""
    },
    ".gvimrc": {
      "name": "Gvimrc",
      "cterm_color": "28",
      "color": "#019833",
      "icon": ""
    },
    ".SRCINFO": {
      "name": "SRCINFO",
      "cterm_color": "67",
      "color": "#0F94D2",
      "icon": "󰣇"
    },
    "svelte.config.js": {
      "name": "SvelteConfig",
      "cterm_color": "196",
      "color": "#FF3E00",
      "icon": ""
    },
    "security.md": {
      "name": "Security",
      "cterm_color": "251",
      "color": "#BEC4C9",
      "icon": "󰒃"
    },
    "Directory.Build.targets": {
      "name": "BuildTargets",
      "cterm_color": "75",
      "color": "#00A2FF",
      "icon": ""
    },
    "i3status.conf": {
      "name": "i3",
      "cterm_color": "255",
      "color": "#E8EBEE",
      "icon": ""
    },
    "cmakelists.txt": {
      "name": "CMakeLists",
      "cterm_color": "254",
      "color": "#DCE3EB",
      "icon": ""
    },
    "robots.txt": {
      "name": "RobotsTxt",
      "cterm_color": "60",
      "color": "#5D7096",
      "icon": "󰚩"
    },
    "gulpfile.ts": {
      "name": "Gulpfile",
      "cterm_color": "167",
      "color": "#CC3E44",
      "icon": ""
    },
    ".dockerignore": {
      "name": "Dockerfile",
      "cterm_color": "68",
      "color": "#458EE6",
      "icon": "󰡨"
    },
    "rmd": {
      "name": "Rmd",
      "cterm_color": "74",
      "color": "#519ABA",
      "icon": ""
    },
    "nuxt.config.ts": {
      "name": "NuxtConfig",
      "cterm_color": "42",
      "color": "#00C58E",
      "icon": "󱄆"
    },
    "gruntfile.js": {
      "name": "Gruntfile",
      "cterm_color": "166",
      "color": "#E37933",
      "icon": ""
    },
    "prisma.config.ts": {
      "name": "PrismaConfig",
      "cterm_color": "62",
      "color": "#5A67D8",
      "icon": ""
    },
    "cantorrc": {
      "name": "Cantorrc",
      "cterm_color": "32",
      "color": "#1C99F3",
      "icon": ""
    },
    "tailwind.config.mjs": {
      "name": "TailwindConfig",
      "cterm_color": "45",
      "color": "#20C2E3",
      "icon": "󱏿"
    },
    "hyprsunset.conf": {
      "name": "Hyprsunset",
      "cterm_color": "37",
      "color": "#00AAAE",
      "icon": ""
    },
    "readme": {
      "name": "Readme",
      "cterm_color": "255",
      "color": "#EDEDED",
      "icon": "󰂺"
    },
    "py.typed": {
      "name": "Py.typed",
      "cterm_color": "214",
      "color": "#FFBC03",
      "icon": ""
    },
    "procfile": {
      "name": "Procfile",
      "cterm_color": "140",
      "color": "#A074C4",
      "icon": ""
    },
    "eslint.config.ts": {
      "name": "Eslintrc",
      "cterm_color": "56",
      "color": "#4B32C3",
      "icon": ""
    },
    "ionic.config.json": {
      "name": "Ionic",
      "cterm_color": "33",
      "color": "#4F8FF7",
      "icon": ""
    },
    "prettier.config.ts": {
      "name": "PrettierConfig",
      "cterm_color": "33",
      "color": "#4285F4",
      "icon": ""
    },
    "index.theme": {
      "name": "IndexTheme",
      "cterm_color": "35",
      "color": "#2DB96F",
      "icon": ""
    },
    "prettier.config.cjs": {
      "name": "PrettierConfig",
      "cterm_color": "33",
      "color": "#4285F4",
      "icon": ""
    },
    "pom.xml": {
      "name": "Maven",
      "cterm_color": "52",
      "color": "#7A0D21",
      "icon": ""
    },
    "gruntfile.ts": {
      "name": "Gruntfile",
      "cterm_color": "166",
      "color": "#E37933",
      "icon": ""
    },
    "package-lock.json": {
      "name": "PackageLockJson",
      "cterm_color": "52",
      "color": "#7A0D21",
      "icon": ""
    },
    "gtkrc": {
      "name": "GTK",
      "cterm_color": "231",
      "color": "#FFFFFF",
      "icon": ""
    },
    ".xsession": {
      "name": "Xsession",
      "cterm_color": "196",
      "color": "#E54D18",
      "icon": ""
    },
    "Directory.Packages.props": {
      "name": "PackagesProps",
      "cterm_color": "75",
      "color": "#00A2FF",
      "icon": ""
    },
    "brewfile": {
      "name": "Brewfile",
      "cterm_color": "52",
      "color": "#701516",
      "icon": ""
    },
    "playwright.config.mts": {
      "name": "PlaywrightConfig",
      "cterm_color": "34",
      "color": "#2FAD33",
      "icon": ""
    },
    "bun.lock": {
      "name": "BunLockfile",
      "cterm_color": "253",
      "color": "#EADCD1",
      "icon": ""
    },
    ".justfile": {
      "name": "Justfile",
      "cterm_color": "66",
      "color": "#6D8086",
      "icon": ""
    },
    "playwright.config.mjs": {
      "name": "PlaywrightConfig",
      "cterm_color": "34",
      "color": "#2FAD33",
      "icon": ""
    },
    ".prettierrc.js": {
      "name": "PrettierConfig",
      "cterm_color": "33",
      "color": "#4285F4",
      "icon": ""
    },
    ".gitconfig": {
      "name": "GitConfig",
      "cterm_color": "196",
      "color": "#F54D27",
      "icon": ""
    },
    "kalgebrarc": {
      "name": "Kalgebrarc",
      "cterm_color": "32",
      "color": "#1C99F3",
      "icon": ""
    },
    "nuxt.config.mjs": {
      "name": "NuxtConfig",
      "cterm_color": "42",
      "color": "#00C58E",
      "icon": "󱄆"
    },
    "platformio.ini": {
      "name": "Platformio",
      "cterm_color": "208",
      "color": "#F6822B",
      "icon": ""
    },
    ".bash_profile": {
      "name": "BashProfile",
      "cterm_color": "113",
      "color": "#89E051",
      "icon": ""
    },
    "build.gradle": {
      "name": "GradleBuildScript",
      "cterm_color": "24",
      "color": "#005F87",
      "icon": ""
    },
    "package.json": {
      "name": "PackageJson",
      "cterm_color": "197",
      "color": "#E8274B",
      "icon": ""
    },
    "playwright.config.ts": {
      "name": "PlaywrightConfig",
      "cterm_color": "34",
      "color": "#2FAD33",
      "icon": ""
    },
    "next.config.js": {
      "name": "NextConfigJs",
      "cterm_color": "231",
      "color": "#FFFFFF",
      "icon": ""
    },
    "nuxt.config.js": {
      "name": "NuxtConfig",
      "cterm_color": "42",
      "color": "#00C58E",
      "icon": "󱄆"
    },
    ".git-blame-ignore-revs": {
      "name": "GitBlameIgnore",
      "cterm_color": "196",
      "color": "#F54D27",
      "icon": ""
    },
    "node_modules": {
      "name": "NodeModules",
      "cterm_color": "197",
      "color": "#E8274B",
      "icon": ""
    },
    "next.config.ts": {
      "name": "NextConfigTs",
      "cterm_color": "231",
      "color": "#FFFFFF",
      "icon": ""
    },
    "go.mod": {
      "name": "GoMod",
      "cterm_color": "38",
      "color": "#00ADD8",
      "icon": ""
    },
    ".settings.json": {
      "name": "SettingsJson",
      "cterm_color": "98",
      "color": "#854CC7",
      "icon": ""
    },
    "favicon.ico": {
      "name": "Favicon",
      "cterm_color": "185",
      "color": "#CBCB41",
      "icon": ""
    },
    "kdenliverc": {
      "name": "Kdenliverc",
      "cterm_color": "110",
      "color": "#83B8F2",
      "icon": ""
    },
    "makefile": {
      "name": "Makefile",
      "cterm_color": "66",
      "color": "#6D8086",
      "icon": ""
    },
    "prettier.config.js": {
      "name": "PrettierConfig",
      "cterm_color": "33",
      "color": "#4285F4",
      "icon": ""
    },
    "kritarc": {
      "name": "Kritarc",
      "cterm_color": "201",
      "color": "#F245FB",
      "icon": ""
    },
    "kritadisplayrc": {
      "name": "Kritadisplayrc",
      "cterm_color": "201",
      "color": "#F245FB",
      "icon": ""
    },
    "mpv.conf": {
      "name": "Mpv",
      "cterm_color": "53",
      "color": "#3B1342",
      "icon": ""
    },
    "kdenlive-layoutsrc": {
      "name": "KdenliveLayoutsrc",
      "cterm_color": "110",
      "color": "#83B8F2",
      "icon": ""
    },
    "playwright.config.cjs": {
      "name": "PlaywrightConfig",
      "cterm_color": "34",
      "color": "#2FAD33",
      "icon": ""
    },
    "tmux.conf": {
      "name": "Tmux",
      "cterm_color": "34",
      "color": "#14BA19",
      "icon": ""
    },
    ".zprofile": {
      "name": "Zshprofile",
      "cterm_color": "113",
      "color": "#89E051",
      "icon": ""
    },
    "lxqt.conf": {
      "name": "LXQtConfigFile",
      "cterm_color": "32",
      "color": "#0192D3",
      "icon": ""
    },
    ".mailmap": {
      "name": "Mailmap",
      "cterm_color": "196",
      "color": "#F54D27",
      "icon": "󰊢"
    },
    "security": {
      "name": "Security",
      "cterm_color": "251",
      "color": "#BEC4C9",
      "icon": "󰒃"
    },
    "go.sum": {
      "name": "GoSum",
      "cterm_color": "38",
      "color": "#00ADD8",
      "icon": ""
    },
    ".prettierrc.json": {
      "name": "PrettierConfig",
      "cterm_color": "33",
      "color": "#4285F4",
      "icon": ""
    },
    "config": {
      "name": "Config",
      "cterm_color": "66",
      "color": "#6D8086",
      "icon": ""
    },
    "FreeCAD.conf": {
      "name": "FreeCADConfig",
      "cterm_color": "160",
      "color": "#CB333B",
      "icon": ""
    },
    "i3blocks.conf": {
      "name": "i3",
      "cterm_color": "255",
      "color": "#E8EBEE",
      "icon": ""
    },
    "commitlint.config.js": {
      "name": "CommitlintConfig",
      "cterm_color": "30",
      "color": "#2B9689",
      "icon": "󰜘"
    },
    "i18n.config.js": {
      "name": "I18nConfig",
      "cterm_color": "104",
      "color": "#7986CB",
      "icon": "󰗊"
    },
    ".pnpmfile.cjs": {
      "name": "PNPMFile",
      "cterm_color": "214",
      "color": "#F9AD02",
      "icon": ""
    },
    ".luacheckrc": {
      "name": "Luacheckrc",
      "cterm_color": "75",
      "color": "#00A2FF",
      "icon": ""
    },
    "vitest.config.js": {
      "name": "VitestConfig",
      "cterm_color": "106",
      "color": "#739B1B",
      "icon": ""
    },
    "code_of_conduct.md": {
      "name": "CodeOfConduct",
      "cterm_color": "161",
      "color": "#E41662",
      "icon": ""
    },
    "hyprland.conf": {
      "name": "Hyprland",
      "cterm_color": "37",
      "color": "#00AAAE",
      "icon": ""
    },
    "dune": {
      "name": "Dunefile",
      "cterm_color": "124",
      "color": "#8a421e",
      "icon": ""
    },
    "_gvimrc": {
      "name": "Gvimrc",
      "cterm_color": "28",
      "color": "#019833",
      "icon": ""
    },
    "Directory.Build.props": {
      "name": "BuildProps",
      "cterm_color": "75",
      "color": "#00A2FF",
      "icon": ""
    },
    "gradlew": {
      "name": "GradleWrapperScript",
      "cterm_color": "24",
      "color": "#005F87",
      "icon": ""
    },
    "gulpfile.coffee": {
      "name": "Gulpfile",
      "cterm_color": "167",
      "color": "#CC3E44",
      "icon": ""
    },
    "gulpfile.babel.js": {
      "name": "Gulpfile",
      "cterm_color": "167",
      "color": "#CC3E44",
      "icon": ""
    },
    "pnpm-workspace.yaml": {
      "name": "PNPMWorkspace",
      "cterm_color": "214",
      "color": "#F9AD02",
      "icon": ""
    },
    "eslint.config.js": {
      "name": "Eslintrc",
      "cterm_color": "56",
      "color": "#4B32C3",
      "icon": ""
    },
    "dockerfile": {
      "name": "Dockerfile",
      "cterm_color": "68",
      "color": "#458EE6",
      "icon": "󰡨"
    },
    "groovy": {
      "name": "Groovy",
      "cterm_color": "24",
      "color": "#4A687C",
      "icon": ""
    },
    ".gitignore": {
      "name": "GitIgnore",
      "cterm_color": "196",
      "color": "#F54D27",
      "icon": ""
    },
    ".bashrc": {
      "name": "Bashrc",
      "cterm_color": "113",
      "color": "#89E051",
      "icon": ""
    },
    "gulpfile.js": {
      "name": "Gulpfile",
      "cterm_color": "167",
      "color": "#CC3E44",
      "icon": ""
    },
    "gruntfile.coffee": {
      "name": "Gruntfile",
      "cterm_color": "166",
      "color": "#E37933",
      "icon": ""
    },
    "go.work": {
      "name": "GoWork",
      "cterm_color": "38",
      "color": "#00ADD8",
      "icon": ""
    },
    "next.config.cjs": {
      "name": "NextConfigCjs",
      "cterm_color": "231",
      "color": "#FFFFFF",
      "icon": ""
    },
    ".eslintrc": {
      "name": "Eslintrc",
      "cterm_color": "56",
      "color": "#4B32C3",
      "icon": ""
    },
    "commitlint.config.ts": {
      "name": "CommitlintConfig",
      "cterm_color": "30",
      "color": "#2B9689",
      "icon": "󰜘"
    },
    "compose.yml": {
      "name": "Dockerfile",
      "cterm_color": "68",
      "color": "#458EE6",
      "icon": "󰡨"
    },
    "eslint.config.mjs": {
      "name": "Eslintrc",
      "cterm_color": "56",
      "color": "#4B32C3",
      "icon": ""
    },
    "gradle.properties": {
      "name": "GradleProperties",
      "cterm_color": "24",
      "color": "#005F87",
      "icon": ""
    },
    ".clang-format": {
      "name": "ClangConfig",
      "cterm_color": "66",
      "color": "#6D8086",
      "icon": ""
    },
    "docker-compose.yml": {
      "name": "Dockerfile",
      "cterm_color": "68",
      "color": "#458EE6",
      "icon": "󰡨"
    },
    "copying.lesser": {
      "name": "License",
      "cterm_color": "185",
      "color": "#CBCB41",
      "icon": ""
    },
    "copying": {
      "name": "License",
      "cterm_color": "185",
      "color": "#CBCB41",
      "icon": ""
    },
    "fp-lib-table": {
      "name": "KiCadFootprintTable",
      "cterm_color": "231",
      "color": "#FFFFFF",
      "icon": ""
    },
    ".nuxtrc": {
      "name": "NuxtConfig",
      "cterm_color": "42",
      "color": "#00C58E",
      "icon": "󱄆"
    },
    "gnumakefile": {
      "name": "Makefile",
      "cterm_color": "66",
      "color": "#6D8086",
      "icon": ""
    },
    "i18n.config.ts": {
      "name": "I18nConfig",
      "cterm_color": "104",
      "color": "#7986CB",
      "icon": "󰗊"
    },
    ".pylintrc": {
      "name": "PyLintConfig",
      "cterm_color": "66",
      "color": "#6D8086",
      "icon": ""
    },
    "build.zig.zon": {
      "name": "ZigObjectNotation",
      "cterm_color": "172",
      "color": "#F69A1B",
      "icon": ""
    },
    ".prettierrc.mjs": {
      "name": "PrettierConfig",
      "cterm_color": "33",
      "color": "#4285F4",
      "icon": ""
    },
    "hyprpaper.conf": {
      "name": "Hyprpaper",
      "cterm_color": "37",
      "color": "#00AAAE",
      "icon": ""
    },
    "QtProject.conf": {
      "name": "Qt",
      "cterm_color": "77",
      "color": "#40CD52",
      "icon": ""
    },
    ".ds_store": {
      "name": "DsStore",
      "cterm_color": "239",
      "color": "#41535B",
      "icon": ""
    },
    "Jenkinsfile": {
      "name": "Jenkins",
      "cterm_color": "160",
      "color": "#D33833",
      "icon": ""
    },
    "Gemfile": {
      "name": "Gemfile",
      "cterm_color": "52",
      "color": "#701516",
      "icon": ""
    },
    "workspace": {
      "name": "BazelWorkspace",
      "cterm_color": "113",
      "color": "#89E051",
      "icon": ""
    },
    "vite.config.js": {
      "name": "ViteConfig",
      "cterm_color": "214",
      "color": "#FFA800",
      "icon": ""
    },
    ".nanorc": {
      "name": "Nano",
      "cterm_color": "54",
      "color": "#440077",
      "icon": ""
    },
    ".prettierrc.yaml": {
      "name": "PrettierConfig",
      "cterm_color": "33",
      "color": "#4285F4",
      "icon": ""
    },
    "bitbucket-pipelines.yml": {
      "name": "BitbucketPipelinesConfig",
      "cterm_color": "33",
      "color": "#2684FF",
      "icon": "󰂨"
    },
    "playwright.config.cts": {
      "name": "PlaywrightConfig",
      "cterm_color": "34",
      "color": "#2FAD33",
      "icon": ""
    },
    "nuxt.config.cjs": {
      "name": "NuxtConfig",
      "cterm_color": "42",
      "color": "#00C58E",
      "icon": "󱄆"
    },
    ".eslintignore": {
      "name": "EslintIgnore",
      "cterm_color": "56",
      "color": "#4B32C3",
      "icon": ""
    }
  },
  "icons_by_file_extension": {
    "txt": {
      "name": "Txt",
      "icon": "󰈙",
      "cterm_color": "113",
      "color": "#89E051"
    },
    "kicad_dru": {
      "name": "KiCad",
      "icon": "",
      "cterm_color": "231",
      "color": "#FFFFFF"
    },
    "cbl": {
      "name": "Cobol",
      "icon": "",
      "cterm_color": "25",
      "color": "#005CA5"
    },
    "mpp": {
      "name": "Mpp",
      "icon": "",
      "cterm_color": "74",
      "color": "#519ABA"
    },
    "cljc": {
      "name": "ClojureC",
      "icon": "",
      "cterm_color": "113",
      "color": "#8DC149"
    },
    "jsonl": {
      "name": "Jsonl",
      "icon": "",
      "cterm_color": "185",
      "color": "#CBCB41"
    },
    "exs": {
      "name": "Exs",
      "icon": "",
      "cterm_color": "140",
      "color": "#A074C4"
    },
    "liquid": {
      "name": "Liquid",
      "icon": "",
      "cterm_color": "106",
      "color": "#95BF47"
    },
    "vue": {
      "name": "Vue",
      "icon": "",
      "cterm_color": "113",
      "color": "#8DC149"
    },
    "hrl": {
      "name": "Hrl",
      "icon": "",
      "cterm_color": "163",
      "color": "#B83998"
    },
    "app": {
      "name": "App",
      "icon": "",
      "cterm_color": "124",
      "color": "#9F0500"
    },
    "stories.vue": {
      "name": "StorybookVue",
      "icon": "",
      "cterm_color": "204",
      "color": "#FF4785"
    },
    "avi": {
      "name": "AudioVideoInterleave",
      "icon": "",
      "cterm_color": "208",
      "color": "#FD971F"
    },
    "makefile": {
      "name": "Makefile",
      "icon": "",
      "cterm_color": "66",
      "color": "#6D8086"
    },
    "hpp": {
      "name": "Hpp",
      "icon": "",
      "cterm_color": "140",
      "color": "#A074C4"
    },
    "ino": {
      "name": "Arduino",
      "icon": "",
      "cterm_color": "73",
      "color": "#56B6C2"
    },
    "drl": {
      "name": "Drools",
      "icon": "",
      "cterm_color": "217",
      "color": "#FFAFAF"
    },
    "epp": {
      "name": "Epp",
      "icon": "",
      "cterm_color": "214",
      "color": "#FFA61A"
    },
    "gv": {
      "name": "Gv",
      "icon": "󱁉",
      "cterm_color": "24",
      "color": "#30638E"
    },
    "cpp": {
      "name": "Cpp",
      "icon": "",
      "cterm_color": "74",
      "color": "#519ABA"
    },
    "stories.jsx": {
      "name": "StorybookJsx",
      "icon": "",
      "cterm_color": "204",
      "color": "#FF4785"
    },
    "git": {
      "name": "GitLogo",
      "icon": "",
      "cterm_color": "196",
      "color": "#F14C28"
    },
    "tgz": {
      "name": "Tgz",
      "icon": "",
      "cterm_color": "214",
      "color": "#ECA517"
    },
    "ical": {
      "name": "Ical",
      "icon": "",
      "cterm_color": "18",
      "color": "#2B2E83"
    },
    "R": {
      "name": "R",
      "icon": "󰟔",
      "cterm_color": "25",
      "color": "#2266BA"
    },
    "ogv": {
      "name": "OggVideo",
      "icon": "",
      "cterm_color": "208",
      "color": "#FD971F"
    },
    "strings": {
      "name": "Localization",
      "icon": "",
      "cterm_color": "31",
      "color": "#2596BE"
    },
    "bmp": {
      "name": "Bmp",
      "icon": "",
      "cterm_color": "140",
      "color": "#A074C4"
    },
    "styl": {
      "name": "Styl",
      "icon": "",
      "cterm_color": "113",
      "color": "#8DC149"
    },
    "ex": {
      "name": "Ex",
      "icon": "",
      "cterm_color": "140",
      "color": "#A074C4"
    },
    "d": {
      "name": "D",
      "icon": "",
      "cterm_color": "124",
      "color": "#B03931"
    },
    "c": {
      "name": "C",
      "icon": "",
      "cterm_color": "111",
      "color": "#599EFF"
    },
    "huff": {
      "name": "Huff",
      "icon": "󰡘",
      "cterm_color": "56",
      "color": "#4242C7"
    },
    "pyw": {
      "name": "Pyw",
      "icon": "",
      "cterm_color": "39",
      "color": "#5AA7E4"
    },
    "a": {
      "name": "StaticLibraryArchive",
      "icon": "",
      "cterm_color": "253",
      "color": "#DCDDD6"
    },
    "bicep": {
      "name": "Bicep",
      "icon": "",
      "cterm_color": "74",
      "color": "#519ABA"
    },
    "download": {
      "name": "Download",
      "icon": "",
      "cterm_color": "43",
      "color": "#44CDA8"
    },
    "pyo": {
      "name": "Pyo",
      "icon": "",
      "cterm_color": "222",
      "color": "#FFE291"
    },
    "cu": {
      "name": "cuda",
      "icon": "",
      "cterm_color": "113",
      "color": "#89E051"
    },
    "h": {
      "name": "H",
      "icon": "",
      "cterm_color": "140",
      "color": "#A074C4"
    },
    "blend": {
      "name": "Blender",
      "icon": "󰂫",
      "cterm_color": "208",
      "color": "#EA7600"
    },
    "zip": {
      "name": "Zip",
      "icon": "",
      "cterm_color": "214",
      "color": "#ECA517"
    },
    "unity": {
      "name": "Unity",
      "icon": "",
      "cterm_color": "231",
      "color": "#FDFDFD"
    },
    "zig": {
      "name": "Zig",
      "icon": "",
      "cterm_color": "172",
      "color": "#F69A1B"
    },
    "yml": {
      "name": "Yml",
      "icon": "",
      "cterm_color": "160",
      "color": "#D70000"
    },
    "m": {
      "name": "ObjectiveC",
      "icon": "",
      "cterm_color": "111",
      "color": "#599EFF"
    },
    "xz": {
      "name": "Xz",
      "icon": "",
      "cterm_color": "214",
      "color": "#ECA517"
    },
    "ifc": {
      "name": "Ifc",
      "icon": "󰻫",
      "cterm_color": "101",
      "color": "#839463"
    },
    "xul": {
      "name": "Xul",
      "icon": "",
      "cterm_color": "166",
      "color": "#E37933"
    },
    "ebuild": {
      "name": "GentooBuild",
      "icon": "",
      "cterm_color": "60",
      "color": "#4C416E"
    },
    "f#": {
      "name": "Fsharp",
      "icon": "",
      "cterm_color": "74",
      "color": "#519ABA"
    },
    "fish": {
      "name": "Fish",
      "icon": "",
      "cterm_color": "240",
      "color": "#4D5A5E"
    },
    "scm": {
      "name": "Scheme",
      "icon": "󰘧",
      "cterm_color": "255",
      "color": "#EEEEEE"
    },
    "tbc": {
      "name": "Tcl",
      "icon": "󰛓",
      "cterm_color": "25",
      "color": "#1E5CB3"
    },
    "slim": {
      "name": "Slim",
      "icon": "",
      "cterm_color": "196",
      "color": "#E34C26"
    },
    "pyi": {
      "name": "Pyi",
      "icon": "",
      "cterm_color": "214",
      "color": "#FFBC03"
    },
    "xpi": {
      "name": "Xpi",
      "icon": "",
      "cterm_color": "196",
      "color": "#FF1B01"
    },
    "astro": {
      "name": "Astro",
      "icon": "",
      "cterm_color": "197",
      "color": "#E23F67"
    },
    "lrc": {
      "name": "Lrc",
      "icon": "󰨖",
      "cterm_color": "214",
      "color": "#FFB713"
    },
    "vala": {
      "name": "Vala",
      "icon": "",
      "cterm_color": "91",
      "color": "#7B3DB9"
    },
    "tmpl": {
      "name": "Template",
      "icon": "",
      "cterm_color": "178",
      "color": "#DBBD30"
    },
    "xm": {
      "name": "Logos",
      "icon": "",
      "cterm_color": "74",
      "color": "#519ABA"
    },
    "f90": {
      "name": "Fortran",
      "icon": "󱈚",
      "cterm_color": "97",
      "color": "#734F96"
    },
    "fods": {
      "name": "LibreOfficeCalc",
      "icon": "",
      "cterm_color": "119",
      "color": "#78FC4E"
    },
    "elf": {
      "name": "Elf",
      "icon": "",
      "cterm_color": "124",
      "color": "#9F0500"
    },
    "pcm": {
      "name": "PulseCodeModulation",
      "icon": "",
      "cterm_color": "24",
      "color": "#0075AA"
    },
    "kdenlivetitle": {
      "name": "Kdenlive",
      "icon": "",
      "cterm_color": "110",
      "color": "#83B8F2"
    },
    "xcstrings": {
      "name": "XcLocalization",
      "icon": "",
      "cterm_color": "31",
      "color": "#2596BE"
    },
    "ccm": {
      "name": "CPlusPlusModule",
      "icon": "",
      "cterm_color": "204",
      "color": "#F34B7D"
    },
    "aac": {
      "name": "AdvancedAudioCoding",
      "icon": "",
      "cterm_color": "39",
      "color": "#00AFFF"
    },
    "kicad_prl": {
      "name": "KiCad",
      "icon": "",
      "cterm_color": "231",
      "color": "#FFFFFF"
    },
    "xcplayground": {
      "name": "XcPlayground",
      "icon": "",
      "cterm_color": "166",
      "color": "#E37933"
    },
    "xcf": {
      "name": "GIMP",
      "icon": "",
      "cterm_color": "240",
      "color": "#635B46"
    },
    "cfc": {
      "name": "ColdFusionScript",
      "icon": "",
      "cterm_color": "38",
      "color": "#01A4BA"
    },
    "less": {
      "name": "Less",
      "icon": "",
      "cterm_color": "54",
      "color": "#563D7C"
    },
    "hh": {
      "name": "Hh",
      "icon": "",
      "cterm_color": "140",
      "color": "#A074C4"
    },
    "xaml": {
      "name": "Xaml",
      "icon": "󰙳",
      "cterm_color": "56",
      "color": "#512BD4"
    },
    "hx": {
      "name": "Haxe",
      "icon": "",
      "cterm_color": "208",
      "color": "#EA8220"
    },
    "wvc": {
      "name": "WavPackCorrection",
      "icon": "",
      "cterm_color": "39",
      "color": "#00AFFF"
    },
    "pck": {
      "name": "PackedResource",
      "icon": "",
      "cterm_color": "66",
      "color": "#6D8086"
    },
    "eot": {
      "name": "EmbeddedOpenTypeFont",
      "icon": "",
      "cterm_color": "255",
      "color": "#ECECEC"
    },
    "docx": {
      "name": "Docx",
      "icon": "󰈬",
      "cterm_color": "26",
      "color": "#185ABD"
    },
    "sqlite3": {
      "name": "Sql",
      "icon": "",
      "cterm_color": "188",
      "color": "#DAD8D8"
    },
    "wv": {
      "name": "WavPack",
      "icon": "",
      "cterm_color": "39",
      "color": "#00AFFF"
    },
    "cxxm": {
      "name": "Cxxm",
      "icon": "",
      "cterm_color": "74",
      "color": "#519ABA"
    },
    "dot": {
      "name": "Dot",
      "icon": "󱁉",
      "cterm_color": "24",
      "color": "#30638E"
    },
    "tsconfig": {
      "name": "TypoScriptConfig",
      "icon": "",
      "cterm_color": "208",
      "color": "#FF8700"
    },
    "wrz": {
      "name": "VRML",
      "icon": "󰆧",
      "cterm_color": "102",
      "color": "#888888"
    },
    "stl": {
      "name": "3DObjectFile",
      "icon": "󰆧",
      "cterm_color": "102",
      "color": "#888888"
    },
    "wrl": {
      "name": "VRML",
      "icon": "󰆧",
      "cterm_color": "102",
      "color": "#888888"
    },
    "gz": {
      "name": "Gz",
      "icon": "",
      "cterm_color": "214",
      "color": "#ECA517"
    },
    "woff2": {
      "name": "WebOpenFontFormat",
      "icon": "",
      "cterm_color": "255",
      "color": "#ECECEC"
    },
    "stories.mjs": {
      "name": "StorybookMjs",
      "icon": "",
      "cterm_color": "204",
      "color": "#FF4785"
    },
    "fctb": {
      "name": "FreeCAD",
      "icon": "",
      "cterm_color": "160",
      "color": "#CB333B"
    },
    "asm": {
      "name": "ASM",
      "icon": "",
      "cterm_color": "31",
      "color": "#0091BD"
    },
    "ogx": {
      "name": "OggMultiplex",
      "icon": "",
      "cterm_color": "208",
      "color": "#FD971F"
    },
    "wmv": {
      "name": "WindowsMediaVideo",
      "icon": "",
      "cterm_color": "208",
      "color": "#FD971F"
    },
    "terminal": {
      "name": "Terminal",
      "icon": "",
      "cterm_color": "34",
      "color": "#31B53E"
    },
    "webpack": {
      "name": "Webpack",
      "icon": "󰜫",
      "cterm_color": "74",
      "color": "#519ABA"
    },
    "v": {
      "name": "Verilog",
      "icon": "󰍛",
      "cterm_color": "28",
      "color": "#019833"
    },
    "webmanifest": {
      "name": "Webmanifest",
      "icon": "",
      "cterm_color": "185",
      "color": "#F1E05A"
    },
    "webm": {
      "name": "Webm",
      "icon": "",
      "cterm_color": "208",
      "color": "#FD971F"
    },
    "wav": {
      "name": "WaveformAudioFile",
      "icon": "",
      "cterm_color": "39",
      "color": "#00AFFF"
    },
    "wasm": {
      "name": "Wasm",
      "icon": "",
      "cterm_color": "62",
      "color": "#5C4CDB"
    },
    "ape": {
      "name": "MonkeysAudio",
      "icon": "",
      "cterm_color": "39",
      "color": "#00AFFF"
    },
    "pot": {
      "name": "Localization",
      "icon": "",
      "cterm_color": "31",
      "color": "#2596BE"
    },
    "skp": {
      "name": "SketchUp",
      "icon": "󰻫",
      "cterm_color": "101",
      "color": "#839463"
    },
    "license": {
      "name": "License",
      "icon": "",
      "cterm_color": "185",
      "color": "#CBCB41"
    },
    "vsix": {
      "name": "Vsix",
      "icon": "",
      "cterm_color": "98",
      "color": "#854CC7"
    },
    "vsh": {
      "name": "Vlang",
      "icon": "",
      "cterm_color": "67",
      "color": "#5D87BF"
    },
    "vim": {
      "name": "Vim",
      "icon": "",
      "cterm_color": "28",
      "color": "#019833"
    },
    "ai": {
      "name": "Ai",
      "icon": "",
      "cterm_color": "185",
      "color": "#CBCB41"
    },
    "fctl": {
      "name": "FreeCAD",
      "icon": "",
      "cterm_color": "160",
      "color": "#CB333B"
    },
    "markdown": {
      "name": "Markdown",
      "icon": "",
      "cterm_color": "253",
      "color": "#DDDDDD"
    },
    "cts": {
      "name": "Cts",
      "icon": "",
      "cterm_color": "74",
      "color": "#519ABA"
    },
    "config.ru": {
      "name": "ConfigRu",
      "icon": "",
      "cterm_color": "52",
      "color": "#701516"
    },
    "stp": {
      "name": "Stp",
      "icon": "󰻫",
      "cterm_color": "101",
      "color": "#839463"
    },
    "feature": {
      "name": "Feature",
      "icon": "",
      "cterm_color": "34",
      "color": "#00A818"
    },
    "cfg": {
      "name": "Configuration",
      "icon": "",
      "cterm_color": "66",
      "color": "#6D8086"
    },
    "mov": {
      "name": "MOV",
      "icon": "",
      "cterm_color": "208",
      "color": "#FD971F"
    },
    "ads": {
      "name": "AdaSpecification",
      "icon": "",
      "cterm_color": "140",
      "color": "#A074C4"
    },
    "vh": {
      "name": "Verilog",
      "icon": "󰍛",
      "cterm_color": "28",
      "color": "#019833"
    },
    "blp": {
      "name": "Blueprint",
      "icon": "󰺾",
      "cterm_color": "68",
      "color": "#5796E2"
    },
    "bz": {
      "name": "Bz",
      "icon": "",
      "cterm_color": "214",
      "color": "#ECA517"
    },
    "lff": {
      "name": "LibrecadFontFile",
      "icon": "",
      "cterm_color": "255",
      "color": "#ECECEC"
    },
    "torrent": {
      "name": "Torrent",
      "icon": "",
      "cterm_color": "43",
      "color": "#44CDA8"
    },
    "rmd": {
      "name": "Rmd",
      "icon": "",
      "cterm_color": "74",
      "color": "#519ABA"
    },
    "mkv": {
      "name": "Mkv",
      "icon": "",
      "cterm_color": "208",
      "color": "#FD971F"
    },
    "webp": {
      "name": "Webp",
      "icon": "",
      "cterm_color": "140",
      "color": "#A074C4"
    },
    "bin": {
      "name": "Bin",
      "icon": "",
      "cterm_color": "124",
      "color": "#9F0500"
    },
    "svg": {
      "name": "Svg",
      "icon": "󰜡",
      "cterm_color": "214",
      "color": "#FFB13B"
    },
    "hxx": {
      "name": "Hxx",
      "icon": "",
      "cterm_color": "140",
      "color": "#A074C4"
    },
    "ui": {
      "name": "UI",
      "icon": "",
      "cterm_color": "27",
      "color": "#015BF0"
    },
    "oga": {
      "name": "OggVorbis",
      "icon": "",
      "cterm_color": "24",
      "color": "#0075AA"
    },
    "apk": {
      "name": "apk",
      "icon": "",
      "cterm_color": "35",
      "color": "#34A853"
    },
    "🔥": {
      "name": "Mojo",
      "icon": "",
      "cterm_color": "196",
      "color": "#FF4C1F"
    },
    "cxx": {
      "name": "Cxx",
      "icon": "",
      "cterm_color": "74",
      "color": "#519ABA"
    },
    "gradle": {
      "name": "Gradle",
      "icon": "",
      "cterm_color": "24",
      "color": "#005F87"
    },
    "ods": {
      "name": "LibreOfficeCalc",
      "icon": "",
      "cterm_color": "119",
      "color": "#78FC4E"
    },
    "eex": {
      "name": "Eex",
      "icon": "",
      "cterm_color": "140",
      "color": "#A074C4"
    },
    "typ": {
      "name": "Typst",
      "icon": "",
      "cterm_color": "37",
      "color": "#0DBCC0"
    },
    "avif": {
      "name": "Avif",
      "icon": "",
      "cterm_color": "140",
      "color": "#A074C4"
    },
    "out": {
      "name": "Out",
      "icon": "",
      "cterm_color": "124",
      "color": "#9F0500"
    },
    "ogg": {
      "name": "OggVorbis",
      "icon": "",
      "cterm_color": "24",
      "color": "#0075AA"
    },
    "import": {
      "name": "ImportConfiguration",
      "icon": "",
      "cterm_color": "255",
      "color": "#ECECEC"
    },
    "bazel": {
      "name": "Bazel",
      "icon": "",
      "cterm_color": "113",
      "color": "#89E051"
    },
    "dwg": {
      "name": "AutoCADDwg",
      "icon": "󰻫",
      "cterm_color": "101",
      "color": "#839463"
    },
    "pxi": {
      "name": "Pxi",
      "icon": "",
      "cterm_color": "39",
      "color": "#5AA7E4"
    },
    "ttf": {
      "name": "TrueTypeFont",
      "icon": "",
      "cterm_color": "255",
      "color": "#ECECEC"
    },
    "tsx": {
      "name": "Tsx",
      "icon": "",
      "cterm_color": "26",
      "color": "#1354BF"
    },
    "tscn": {
      "name": "GodotTextScene",
      "icon": "",
      "cterm_color": "66",
      "color": "#6D8086"
    },
    "kdbx": {
      "name": "Kdbx",
      "icon": "",
      "cterm_color": "71",
      "color": "#529B34"
    },
    "heex": {
      "name": "Heex",
      "icon": "",
      "cterm_color": "140",
      "color": "#A074C4"
    },
    "sldprt": {
      "name": "SolidWorksPrt",
      "icon": "󰻫",
      "cterm_color": "101",
      "color": "#839463"
    },
    "hex": {
      "name": "Hexadecimal",
      "icon": "",
      "cterm_color": "27",
      "color": "#2E63FF"
    },
    "erb": {
      "name": "Erb",
      "icon": "",
      "cterm_color": "52",
      "color": "#701516"
    },
    "vi": {
      "name": "LabView",
      "icon": "",
      "cterm_color": "220",
      "color": "#FEC60A"
    },
    "ksh": {
      "name": "Ksh",
      "icon": "",
      "cterm_color": "240",
      "color": "#4D5A5E"
    },
    "sqlite": {
      "name": "Sql",
      "icon": "",
      "cterm_color": "188",
      "color": "#DAD8D8"
    },
    "toml": {
      "name": "Toml",
      "icon": "",
      "cterm_color": "124",
      "color": "#9C4221"
    },
    "spec.jsx": {
      "name": "JavaScriptReactSpec",
      "icon": "",
      "cterm_color": "45",
      "color": "#20C2E3"
    },
    "sh": {
      "name": "Sh",
      "icon": "",
      "cterm_color": "240",
      "color": "#4D5A5E"
    },
    "tfvars": {
      "name": "TFVars",
      "icon": "",
      "cterm_color": "93",
      "color": "#5F43E9"
    },
    "3gp": {
      "name": "3gp",
      "icon": "",
      "cterm_color": "208",
      "color": "#FD971F"
    },
    "tf": {
      "name": "Terraform",
      "icon": "",
      "cterm_color": "93",
      "color": "#5F43E9"
    },
    "csh": {
      "name": "Csh",
      "icon": "",
      "cterm_color": "240",
      "color": "#4D5A5E"
    },
    "tex": {
      "name": "Tex",
      "icon": "",
      "cterm_color": "22",
      "color": "#3D6117"
    },
    "android": {
      "name": "Android",
      "icon": "",
      "cterm_color": "35",
      "color": "#34A853"
    },
    "aiff": {
      "name": "AudioInterchangeFileFormat",
      "icon": "",
      "cterm_color": "39",
      "color": "#00AFFF"
    },
    "diff": {
      "name": "Diff",
      "icon": "",
      "cterm_color": "239",
      "color": "#41535B"
    },
    "7z": {
      "name": "7z",
      "icon": "",
      "cterm_color": "214",
      "color": "#ECA517"
    },
    "norg": {
      "name": "Norg",
      "icon": "",
      "cterm_color": "32",
      "color": "#4878BE"
    },
    "test.tsx": {
      "name": "TypeScriptReactTest",
      "icon": "",
      "cterm_color": "26",
      "color": "#1354BF"
    },
    "apl": {
      "name": "APL",
      "icon": "",
      "cterm_color": "35",
      "color": "#24A148"
    },
    "sldasm": {
      "name": "SolidWorksAsm",
      "icon": "󰻫",
      "cterm_color": "101",
      "color": "#839463"
    },
    "cjs": {
      "name": "Cjs",
      "icon": "",
      "cterm_color": "185",
      "color": "#CBCB41"
    },
    "test.ts": {
      "name": "TestTs",
      "icon": "",
      "cterm_color": "74",
      "color": "#519ABA"
    },
    "ejs": {
      "name": "Ejs",
      "icon": "",
      "cterm_color": "185",
      "color": "#CBCB41"
    },
    "test.jsx": {
      "name": "JavaScriptReactTest",
      "icon": "",
      "cterm_color": "45",
      "color": "#20C2E3"
    },
    "test.js": {
      "name": "TestJs",
      "icon": "",
      "cterm_color": "185",
      "color": "#CBCB41"
    },
    "wma": {
      "name": "WindowsMediaAudio",
      "icon": "",
      "cterm_color": "39",
      "color": "#00AFFF"
    },
    "templ": {
      "name": "Templ",
      "icon": "",
      "cterm_color": "178",
      "color": "#DBBD30"
    },
    "msf": {
      "name": "Thunderbird",
      "icon": "",
      "cterm_color": "33",
      "color": "#137BE1"
    },
    "query": {
      "name": "Query",
      "icon": "",
      "cterm_color": "107",
      "color": "#90A850"
    },
    "tcl": {
      "name": "Tcl",
      "icon": "󰛓",
      "cterm_color": "25",
      "color": "#1E5CB3"
    },
    "desktop": {
      "name": "DesktopEntry",
      "icon": "",
      "cterm_color": "54",
      "color": "#563D7C"
    },
    "svx": {
      "name": "SvelteMarkdown",
      "icon": "",
      "cterm_color": "197",
      "color": "#FF0042"
    },
    "cobol": {
      "name": "Cobol",
      "icon": "",
      "cterm_color": "25",
      "color": "#005CA5"
    },
    "t": {
      "name": "Tor",
      "icon": "",
      "cterm_color": "74",
      "color": "#519ABA"
    },
    "swift": {
      "name": "Swift",
      "icon": "",
      "cterm_color": "166",
      "color": "#E37933"
    },
    "svh": {
      "name": "SystemVerilog",
      "icon": "󰍛",
      "cterm_color": "28",
      "color": "#019833"
    },
    "m3u8": {
      "name": "M3u8",
      "icon": "󰲹",
      "cterm_color": "211",
      "color": "#ED95AE"
    },
    "scad": {
      "name": "OpenSCAD",
      "icon": "",
      "cterm_color": "220",
      "color": "#F9D72C"
    },
    "svelte": {
      "name": "Svelte",
      "icon": "",
      "cterm_color": "196",
      "color": "#FF3E00"
    },
    "bak": {
      "name": "Backup",
      "icon": "󰁯",
      "cterm_color": "66",
      "color": "#6D8086"
    },
    "sv": {
      "name": "SystemVerilog",
      "icon": "󰍛",
      "cterm_color": "28",
      "color": "#019833"
    },
    "nu": {
      "name": "Nushell",
      "icon": "",
      "cterm_color": "36",
      "color": "#3AA675"
    },
    "java": {
      "name": "Java",
      "icon": "",
      "cterm_color": "167",
      "color": "#CC3E44"
    },
    "sublime": {
      "name": "Sublime",
      "icon": "",
      "cterm_color": "166",
      "color": "#E37933"
    },
    "sub": {
      "name": "Sub",
      "icon": "󰨖",
      "cterm_color": "214",
      "color": "#FFB713"
    },
    "jar": {
      "name": "Jar",
      "icon": "",
      "cterm_color": "215",
      "color": "#ffaf67"
    },
    "mjs": {
      "name": "Mjs",
      "icon": "",
      "cterm_color": "185",
      "color": "#F1E05A"
    },
    "magnet": {
      "name": "Magnet",
      "icon": "",
      "cterm_color": "124",
      "color": "#A51B16"
    },
    "el": {
      "name": "Elisp",
      "icon": "",
      "cterm_color": "97",
      "color": "#8172BE"
    },
    "jwmrc": {
      "name": "JWM",
      "icon": "",
      "cterm_color": "32",
      "color": "#0078CD"
    },
    "cache": {
      "name": "Cache",
      "icon": "",
      "cterm_color": "231",
      "color": "#FFFFFF"
    },
    "odf": {
      "name": "LibreOfficeFormula",
      "icon": "",
      "cterm_color": "204",
      "color": "#FF5A96"
    },
    "pdf": {
      "name": "Pdf",
      "icon": "",
      "cterm_color": "124",
      "color": "#B30B00"
    },
    "fodp": {
      "name": "LibreOfficeImpress",
      "icon": "",
      "cterm_color": "215",
      "color": "#FE9C45"
    },
    "vhdl": {
      "name": "VHDL",
      "icon": "󰍛",
      "cterm_color": "28",
      "color": "#019833"
    },
    "stories.tsx": {
      "name": "StorybookTsx",
      "icon": "",
      "cterm_color": "204",
      "color": "#FF4785"
    },
    "jsx": {
      "name": "Jsx",
      "icon": "",
      "cterm_color": "45",
      "color": "#20C2E3"
    },
    "gql": {
      "name": "GraphQL",
      "icon": "",
      "cterm_color": "199",
      "color": "#E535AB"
    },
    "cs": {
      "name": "Cs",
      "icon": "󰌛",
      "cterm_color": "58",
      "color": "#596706"
    },
    "pyd": {
      "name": "Pyd",
      "icon": "",
      "cterm_color": "222",
      "color": "#FFE291"
    },
    "asc": {
      "name": "Asc",
      "icon": "󰦝",
      "cterm_color": "242",
      "color": "#576D7F"
    },
    "bz3": {
      "name": "Bz3",
      "icon": "",
      "cterm_color": "214",
      "color": "#ECA517"
    },
    "woff": {
      "name": "WebOpenFontFormat",
      "icon": "",
      "cterm_color": "255",
      "color": "#ECECEC"
    },
    "otf": {
      "name": "OpenTypeFont",
      "icon": "",
      "cterm_color": "255",
      "color": "#ECECEC"
    },
    "stories.js": {
      "name": "StorybookJavaScript",
      "icon": "",
      "cterm_color": "204",
      "color": "#FF4785"
    },
    "pptx": {
      "name": "Pptx",
      "icon": "󰈧",
      "cterm_color": "160",
      "color": "#CB4A32"
    },
    "elm": {
      "name": "Elm",
      "icon": "",
      "cterm_color": "74",
      "color": "#519ABA"
    },
    "glb": {
      "name": "BinaryGLTF",
      "icon": "",
      "cterm_color": "214",
      "color": "#FFB13B"
    },
    "fsx": {
      "name": "Fsx",
      "icon": "",
      "cterm_color": "74",
      "color": "#519ABA"
    },
    "py": {
      "name": "Py",
      "icon": "",
      "cterm_color": "214",
      "color": "#FFBC03"
    },
    "ste": {
      "name": "Ste",
      "icon": "󰻫",
      "cterm_color": "101",
      "color": "#839463"
    },
    "sln": {
      "name": "Sln",
      "icon": "",
      "cterm_color": "98",
      "color": "#854CC7"
    },
    "gleam": {
      "name": "Gleam",
      "icon": "",
      "cterm_color": "219",
      "color": "#FFAFF3"
    },
    "fcscript": {
      "name": "FreeCAD",
      "icon": "",
      "cterm_color": "160",
      "color": "#CB333B"
    },
    "spec.tsx": {
      "name": "TypeScriptReactSpec",
      "icon": "",
      "cterm_color": "26",
      "color": "#1354BF"
    },
    "eln": {
      "name": "Elisp",
      "icon": "",
      "cterm_color": "97",
      "color": "#8172BE"
    },
    "sql": {
      "name": "Sql",
      "icon": "",
      "cterm_color": "188",
      "color": "#DAD8D8"
    },
    "rkt": {
      "name": "Racket",
      "icon": "󰘧",
      "cterm_color": "124",
      "color": "#9F1D20"
    },
    "md5": {
      "name": "Md5",
      "icon": "󰕥",
      "cterm_color": "103",
      "color": "#8C86AF"
    },
    "clj": {
      "name": "Clojure",
      "icon": "",
      "cterm_color": "113",
      "color": "#8DC149"
    },
    "sha224": {
      "name": "Sha224",
      "icon": "󰕥",
      "cterm_color": "103",
      "color": "#8C86AF"
    },
    "spec.js": {
      "name": "SpecJs",
      "icon": "",
      "cterm_color": "185",
      "color": "#CBCB41"
    },
    "sha384": {
      "name": "Sha384",
      "icon": "󰕥",
      "cterm_color": "103",
      "color": "#8C86AF"
    },
    "sol": {
      "name": "Solidity",
      "icon": "",
      "cterm_color": "74",
      "color": "#519ABA"
    },
    "so": {
      "name": "SharedObject",
      "icon": "",
      "cterm_color": "253",
      "color": "#DCDDD6"
    },
    "sml": {
      "name": "Sml",
      "icon": "󰘧",
      "cterm_color": "166",
      "color": "#E37933"
    },
    "mdx": {
      "name": "Mdx",
      "icon": "",
      "cterm_color": "74",
      "color": "#519ABA"
    },
    "slvs": {
      "name": "SolveSpace",
      "icon": "󰻫",
      "cterm_color": "101",
      "color": "#839463"
    },
    "slnx": {
      "name": "Slnx",
      "icon": "",
      "cterm_color": "98",
      "color": "#854CC7"
    },
    "ssa": {
      "name": "Ssa",
      "icon": "󰨖",
      "cterm_color": "214",
      "color": "#FFB713"
    },
    "kra": {
      "name": "Krita",
      "icon": "",
      "cterm_color": "201",
      "color": "#F245FB"
    },
    "sig": {
      "name": "Sig",
      "icon": "󰘧",
      "cterm_color": "166",
      "color": "#E37933"
    },
    "jpeg": {
      "name": "Jpeg",
      "icon": "",
      "cterm_color": "140",
      "color": "#A074C4"
    },
    "cshtml": {
      "name": "RazorPage",
      "icon": "󱦗",
      "cterm_color": "56",
      "color": "#512BD4"
    },
    "fsi": {
      "name": "Fsi",
      "icon": "",
      "cterm_color": "74",
      "color": "#519ABA"
    },
    "coffee": {
      "name": "Coffee",
      "icon": "",
      "cterm_color": "185",
      "color": "#CBCB41"
    },
    "bzl": {
      "name": "Bzl",
      "icon": "",
      "cterm_color": "113",
      "color": "#89E051"
    },
    "sha512": {
      "name": "Sha512",
      "icon": "󰕥",
      "cterm_color": "103",
      "color": "#8C86AF"
    },
    "flac": {
      "name": "FreeLosslessAudioCodec",
      "icon": "",
      "cterm_color": "24",
      "color": "#0075AA"
    },
    "sha256": {
      "name": "Sha256",
      "icon": "󰕥",
      "cterm_color": "103",
      "color": "#8C86AF"
    },
    "org": {
      "name": "OrgMode",
      "icon": "",
      "cterm_color": "73",
      "color": "#77AA99"
    },
    "spec.ts": {
      "name": "SpecTs",
      "icon": "",
      "cterm_color": "74",
      "color": "#519ABA"
    },
    "brep": {
      "name": "BoundaryRepresentation",
      "icon": "󰻫",
      "cterm_color": "101",
      "color": "#839463"
    },
    "pub": {
      "name": "Pub",
      "icon": "󰷖",
      "cterm_color": "222",
      "color": "#E3C58E"
    },
    "jsonc": {
      "name": "Jsonc",
      "icon": "",
      "cterm_color": "185",
      "color": "#CBCB41"
    },
    "sha1": {
      "name": "Sha1",
      "icon": "󰕥",
      "cterm_color": "103",
      "color": "#8C86AF"
    },
    "tmux": {
      "name": "Tmux",
      "icon": "",
      "cterm_color": "34",
      "color": "#14BA19"
    },
    "vert": {
      "name": "VertexShader",
      "icon": "",
      "cterm_color": "67",
      "color": "#5586A6"
    },
    "cpy": {
      "name": "Cobol",
      "icon": "",
      "cterm_color": "25",
      "color": "#005CA5"
    },
    "xml": {
      "name": "Xml",
      "icon": "󰗀",
      "cterm_color": "166",
      "color": "#E37933"
    },
    "sc": {
      "name": "ScalaScript",
      "icon": "",
      "cterm_color": "167",
      "color": "#CC3E44"
    },
    "cljs": {
      "name": "ClojureJS",
      "icon": "",
      "cterm_color": "74",
      "color": "#519ABA"
    },
    "kicad_sym": {
      "name": "KiCad",
      "icon": "",
      "cterm_color": "231",
      "color": "#FFFFFF"
    },
    "bat": {
      "name": "Bat",
      "icon": "",
      "cterm_color": "191",
      "color": "#C1F12E"
    },
    "fodg": {
      "name": "LibreOfficeGraphics",
      "icon": "",
      "cterm_color": "227",
      "color": "#FFFB57"
    },
    "sass": {
      "name": "Sass",
      "icon": "",
      "cterm_color": "204",
      "color": "#F55385"
    },
    "cuh": {
      "name": "cudah",
      "icon": "",
      "cterm_color": "140",
      "color": "#A074C4"
    },
    "rasi": {
      "name": "Rasi",
      "icon": "",
      "cterm_color": "185",
      "color": "#CBCB41"
    },
    "dll": {
      "name": "Dll",
      "icon": "",
      "cterm_color": "52",
      "color": "#4D2C0B"
    },
    "ics": {
      "name": "Ics",
      "icon": "",
      "cterm_color": "18",
      "color": "#2B2E83"
    },
    "razor": {
      "name": "RazorPage",
      "icon": "󱦘",
      "cterm_color": "56",
      "color": "#512BD4"
    },
    "gpr": {
      "name": "GPRBuildProject",
      "icon": "",
      "cterm_color": "66",
      "color": "#6D8086"
    },
    "kbx": {
      "name": "Kbx",
      "icon": "󰯄",
      "cterm_color": "243",
      "color": "#737672"
    },
    "mustache": {
      "name": "Mustache",
      "icon": "",
      "cterm_color": "166",
      "color": "#E37933"
    },
    "resi": {
      "name": "ReScriptInterface",
      "icon": "",
      "cterm_color": "204",
      "color": "#F55385"
    },
    "res": {
      "name": "ReScript",
      "icon": "",
      "cterm_color": "167",
      "color": "#CC3E44"
    },
    "mp3": {
      "name": "MPEGAudioLayerIII",
      "icon": "",
      "cterm_color": "39",
      "color": "#00AFFF"
    },
    "hurl": {
      "name": "Hurl",
      "icon": "",
      "cterm_color": "198",
      "color": "#FF0288"
    },
    "gnumakefile": {
      "name": "Makefile",
      "icon": "",
      "cterm_color": "66",
      "color": "#6D8086"
    },
    "rproj": {
      "name": "Rproj",
      "icon": "󰗆",
      "cterm_color": "29",
      "color": "#358A5B"
    },
    "rar": {
      "name": "Rar",
      "icon": "",
      "cterm_color": "214",
      "color": "#ECA517"
    },
    "rake": {
      "name": "Rake",
      "icon": "",
      "cterm_color": "52",
      "color": "#701516"
    },
    "igs": {
      "name": "Igs",
      "icon": "󰻫",
      "cterm_color": "101",
      "color": "#839463"
    },
    "elc": {
      "name": "Elisp",
      "icon": "",
      "cterm_color": "97",
      "color": "#8172BE"
    },
    "dump": {
      "name": "Dump",
      "icon": "",
      "cterm_color": "188",
      "color": "#DAD8D8"
    },
    "qrc": {
      "name": "Qt",
      "icon": "",
      "cterm_color": "77",
      "color": "#40CD52"
    },
    "qml": {
      "name": "Qt",
      "icon": "",
      "cterm_color": "77",
      "color": "#40CD52"
    },
    "ifb": {
      "name": "Ifb",
      "icon": "",
      "cterm_color": "18",
      "color": "#2B2E83"
    },
    "qm": {
      "name": "Localization",
      "icon": "",
      "cterm_color": "31",
      "color": "#2596BE"
    },
    "mm": {
      "name": "ObjectiveCPlusPlus",
      "icon": "",
      "cterm_color": "74",
      "color": "#519ABA"
    },
    "pyx": {
      "name": "Pyx",
      "icon": "",
      "cterm_color": "39",
      "color": "#5AA7E4"
    },
    "typoscript": {
      "name": "TypoScript",
      "icon": "",
      "cterm_color": "208",
      "color": "#FF8700"
    },
    "pm": {
      "name": "Pm",
      "icon": "",
      "cterm_color": "74",
      "color": "#519ABA"
    },
    "pyc": {
      "name": "Pyc",
      "icon": "",
      "cterm_color": "222",
      "color": "#FFE291"
    },
    "mo": {
      "name": "Motoko",
      "icon": "",
      "cterm_color": "135",
      "color": "#9772FB"
    },
    "zsh": {
      "name": "Zsh",
      "icon": "",
      "cterm_color": "113",
      "color": "#89E051"
    },
    "frag": {
      "name": "FragmentShader",
      "icon": "",
      "cterm_color": "67",
      "color": "#5586A6"
    },
    "fbx": {
      "name": "3DObjectFile",
      "icon": "󰆧",
      "cterm_color": "102",
      "color": "#888888"
    },
    "stories.svelte": {
      "name": "StorybookSvelte",
      "icon": "",
      "cterm_color": "204",
      "color": "#FF4785"
    },
    "step": {
      "name": "Step",
      "icon": "󰻫",
      "cterm_color": "101",
      "color": "#839463"
    },
    "go": {
      "name": "Go",
      "icon": "",
      "cterm_color": "38",
      "color": "#00ADD8"
    },
    "mp4": {
      "name": "Mp4",
      "icon": "",
      "cterm_color": "208",
      "color": "#FD971F"
    },
    "bicepparam": {
      "name": "BicepParameters",
      "icon": "",
      "cterm_color": "133",
      "color": "#9F74B3"
    },
    "c++": {
      "name": "CPlusPlus",
      "icon": "",
      "cterm_color": "204",
      "color": "#F34B7D"
    },
    "ada": {
      "name": "AdaFile",
      "icon": "",
      "cterm_color": "111",
      "color": "#599EFF"
    },
    "twig": {
      "name": "Twig",
      "icon": "",
      "cterm_color": "113",
      "color": "#8DC149"
    },
    "pxd": {
      "name": "Pxd",
      "icon": "",
      "cterm_color": "39",
      "color": "#5AA7E4"
    },
    "odt": {
      "name": "LibreOfficeWriter",
      "icon": "",
      "cterm_color": "81",
      "color": "#2DCBFD"
    },
    "psd1": {
      "name": "PsManifestfile",
      "icon": "󰨊",
      "cterm_color": "68",
      "color": "#6975C4"
    },
    "po": {
      "name": "Localization",
      "icon": "",
      "cterm_color": "31",
      "color": "#2596BE"
    },
    "psd": {
      "name": "Psd",
      "icon": "",
      "cterm_color": "74",
      "color": "#519ABA"
    },
    "cob": {
      "name": "Cobol",
      "icon": "",
      "cterm_color": "25",
      "color": "#005CA5"
    },
    "rb": {
      "name": "Rb",
      "icon": "",
      "cterm_color": "52",
      "color": "#701516"
    },
    "ps1": {
      "name": "PsScriptfile",
      "icon": "󰨊",
      "cterm_color": "68",
      "color": "#4273CA"
    },
    "fcmat": {
      "name": "FreeCAD",
      "icon": "",
      "cterm_color": "160",
      "color": "#CB333B"
    },
    "tres": {
      "name": "GodotTextResource",
      "icon": "",
      "cterm_color": "66",
      "color": "#6D8086"
    },
    "prisma": {
      "name": "Prisma",
      "icon": "",
      "cterm_color": "62",
      "color": "#5A67D8"
    },
    "prefab": {
      "name": "Prefab",
      "icon": "",
      "cterm_color": "117",
      "color": "#94D4F9"
    },
    "ppt": {
      "name": "Ppt",
      "icon": "󰈧",
      "cterm_color": "160",
      "color": "#CB4A32"
    },
    "applescript": {
      "name": "AppleScript",
      "icon": "",
      "cterm_color": "66",
      "color": "#6D8085"
    },
    "pp": {
      "name": "Pp",
      "icon": "",
      "cterm_color": "214",
      "color": "#FFA61A"
    },
    "cp": {
      "name": "Cp",
      "icon": "",
      "cterm_color": "74",
      "color": "#519ABA"
    },
    "png": {
      "name": "Png",
      "icon": "",
      "cterm_color": "140",
      "color": "#A074C4"
    },
    "ply": {
      "name": "3DObjectFile",
      "icon": "󰆧",
      "cterm_color": "102",
      "color": "#888888"
    },
    "pls": {
      "name": "Pls",
      "icon": "󰲹",
      "cterm_color": "211",
      "color": "#ED95AE"
    },
    "pl": {
      "name": "Pl",
      "icon": "",
      "cterm_color": "74",
      "color": "#519ABA"
    },
    "php": {
      "name": "Php",
      "icon": "",
      "cterm_color": "140",
      "color": "#A074C4"
    },
    "dxf": {
      "name": "AutoCADDxf",
      "icon": "󰻫",
      "cterm_color": "101",
      "color": "#839463"
    },
    "patch": {
      "name": "Patch",
      "icon": "",
      "cterm_color": "239",
      "color": "#41535B"
    },
    "part": {
      "name": "Part",
      "icon": "",
      "cterm_color": "43",
      "color": "#44CDA8"
    },
    "opus": {
      "name": "OpusAudioFile",
      "icon": "",
      "cterm_color": "24",
      "color": "#0075AA"
    },
    "gcode": {
      "name": "GCode",
      "icon": "󰐫",
      "cterm_color": "32",
      "color": "#1471AD"
    },
    "psm1": {
      "name": "PsScriptModulefile",
      "icon": "󰨊",
      "cterm_color": "68",
      "color": "#6975C4"
    },
    "cppm": {
      "name": "Cppm",
      "icon": "",
      "cterm_color": "74",
      "color": "#519ABA"
    },
    "m4v": {
      "name": "M4V",
      "icon": "",
      "cterm_color": "208",
      "color": "#FD971F"
    },
    "fcmacro": {
      "name": "FreeCAD",
      "icon": "",
      "cterm_color": "160",
      "color": "#CB333B"
    },
    "doc": {
      "name": "Doc",
      "icon": "󰈬",
      "cterm_color": "26",
      "color": "#185ABD"
    },
    "odg": {
      "name": "LibreOfficeGraphics",
      "icon": "",
      "cterm_color": "227",
      "color": "#FFFB57"
    },
    "ko": {
      "name": "LinuxKernelObject",
      "icon": "",
      "cterm_color": "253",
      "color": "#DCDDD6"
    },
    "o": {
      "name": "ObjectFile",
      "icon": "",
      "cterm_color": "124",
      "color": "#9F0500"
    },
    "suo": {
      "name": "Suo",
      "icon": "",
      "cterm_color": "98",
      "color": "#854CC7"
    },
    "fcstd1": {
      "name": "FreeCAD",
      "icon": "",
      "cterm_color": "160",
      "color": "#CB333B"
    },
    "http": {
      "name": "HTTP",
      "icon": "",
      "cterm_color": "31",
      "color": "#008EC7"
    },
    "nswag": {
      "name": "Nswag",
      "icon": "",
      "cterm_color": "112",
      "color": "#85EA2D"
    },
    "nix": {
      "name": "Nix",
      "icon": "",
      "cterm_color": "110",
      "color": "#7EBAE4"
    },
    "kdenlive": {
      "name": "Kdenlive",
      "icon": "",
      "cterm_color": "110",
      "color": "#83B8F2"
    },
    "geom": {
      "name": "GeometryShader",
      "icon": "",
      "cterm_color": "67",
      "color": "#5586A6"
    },
    "nim": {
      "name": "Nim",
      "icon": "",
      "cterm_color": "220",
      "color": "#F3D400"
    },
    "env": {
      "name": "Env",
      "icon": "",
      "cterm_color": "227",
      "color": "#FAF743"
    },
    "nfo": {
      "name": "Nfo",
      "icon": "",
      "cterm_color": "230",
      "color": "#FFFFCD"
    },
    "mts": {
      "name": "Mts",
      "icon": "",
      "cterm_color": "74",
      "color": "#519ABA"
    },
    "azcli": {
      "name": "AzureCli",
      "icon": "",
      "cterm_color": "32",
      "color": "#0078D4"
    },
    "bash": {
      "name": "Bash",
      "icon": "",
      "cterm_color": "113",
      "color": "#89E051"
    },
    "lock": {
      "name": "Lock",
      "icon": "",
      "cterm_color": "250",
      "color": "#BBBBBB"
    },
    "fcstd": {
      "name": "FreeCAD",
      "icon": "",
      "cterm_color": "160",
      "color": "#CB333B"
    },
    "vhd": {
      "name": "VHDL",
      "icon": "󰍛",
      "cterm_color": "28",
      "color": "#019833"
    },
    "mojo": {
      "name": "Mojo",
      "icon": "",
      "cterm_color": "196",
      "color": "#FF4C1F"
    },
    "luau": {
      "name": "Luau",
      "icon": "",
      "cterm_color": "75",
      "color": "#00A2FF"
    },
    "mli": {
      "name": "Mli",
      "icon": "",
      "cterm_color": "166",
      "color": "#E37933"
    },
    "ml": {
      "name": "Ml",
      "icon": "",
      "cterm_color": "166",
      "color": "#E37933"
    },
    "bz2": {
      "name": "Bz2",
      "icon": "",
      "cterm_color": "214",
      "color": "#ECA517"
    },
    "mk": {
      "name": "Makefile",
      "icon": "",
      "cterm_color": "66",
      "color": "#6D8086"
    },
    "csv": {
      "name": "Csv",
      "icon": "",
      "cterm_color": "113",
      "color": "#89E051"
    },
    "mint": {
      "name": "Mint",
      "icon": "󰌪",
      "cterm_color": "108",
      "color": "#87C095"
    },
    "crdownload": {
      "name": "Crdownload",
      "icon": "",
      "cterm_color": "43",
      "color": "#44CDA8"
    },
    "spx": {
      "name": "OggSpeexAudio",
      "icon": "",
      "cterm_color": "24",
      "color": "#0075AA"
    },
    "yaml": {
      "name": "Yaml",
      "icon": "",
      "cterm_color": "160",
      "color": "#D70000"
    },
    "pro": {
      "name": "Prolog",
      "icon": "",
      "cterm_color": "179",
      "color": "#E4B854"
    },
    "material": {
      "name": "Material",
      "icon": "",
      "cterm_color": "163",
      "color": "#B83998"
    },
    "m3u": {
      "name": "M3u",
      "icon": "󰲹",
      "cterm_color": "211",
      "color": "#ED95AE"
    },
    "odp": {
      "name": "LibreOfficeImpress",
      "icon": "",
      "cterm_color": "215",
      "color": "#FE9C45"
    },
    "Dockerfile": {
      "name": "Dockerfile",
      "icon": "󰡨",
      "cterm_color": "68",
      "color": "#458EE6"
    },
    "fcbak": {
      "name": "FreeCAD",
      "icon": "",
      "cterm_color": "160",
      "color": "#CB333B"
    },
    "dconf": {
      "name": "Dconf",
      "icon": "",
      "cterm_color": "231",
      "color": "#FFFFFF"
    },
    "bqn": {
      "name": "APL",
      "icon": "",
      "cterm_color": "35",
      "color": "#24A148"
    },
    "svgz": {
      "name": "Svgz",
      "icon": "󰜡",
      "cterm_color": "214",
      "color": "#FFB13B"
    },
    "md": {
      "name": "Md",
      "icon": "",
      "cterm_color": "253",
      "color": "#DDDDDD"
    },
    "aif": {
      "name": "AudioInterchangeFileFormat",
      "icon": "",
      "cterm_color": "39",
      "color": "#00AFFF"
    },
    "bib": {
      "name": "BibTeX",
      "icon": "󱉟",
      "cterm_color": "185",
      "color": "#CBCB41"
    },
    "mobi": {
      "name": "Mobi",
      "icon": "",
      "cterm_color": "215",
      "color": "#EAB16D"
    },
    "luac": {
      "name": "Lua",
      "icon": "",
      "cterm_color": "74",
      "color": "#51A0CF"
    },
    "ebook": {
      "name": "Ebook",
      "icon": "",
      "cterm_color": "215",
      "color": "#EAB16D"
    },
    "krz": {
      "name": "Krita",
      "icon": "",
      "cterm_color": "201",
      "color": "#F245FB"
    },
    "conf": {
      "name": "Conf",
      "icon": "",
      "cterm_color": "66",
      "color": "#6D8086"
    },
    "iges": {
      "name": "Iges",
      "icon": "󰻫",
      "cterm_color": "101",
      "color": "#839463"
    },
    "exe": {
      "name": "Exe",
      "icon": "",
      "cterm_color": "124",
      "color": "#9F0500"
    },
    "lua": {
      "name": "Lua",
      "icon": "",
      "cterm_color": "74",
      "color": "#51A0CF"
    },
    "scala": {
      "name": "Scala",
      "icon": "",
      "cterm_color": "167",
      "color": "#CC3E44"
    },
    "signature": {
      "name": "Signature",
      "icon": "󰘧",
      "cterm_color": "166",
      "color": "#E37933"
    },
    "lib": {
      "name": "Lib",
      "icon": "",
      "cterm_color": "52",
      "color": "#4D2C0B"
    },
    "image": {
      "name": "Image",
      "icon": "",
      "cterm_color": "181",
      "color": "#D0BEC8"
    },
    "lhs": {
      "name": "Lhs",
      "icon": "",
      "cterm_color": "140",
      "color": "#A074C4"
    },
    "scss": {
      "name": "Scss",
      "icon": "",
      "cterm_color": "204",
      "color": "#F55385"
    },
    "leex": {
      "name": "Leex",
      "icon": "",
      "cterm_color": "140",
      "color": "#A074C4"
    },
    "lck": {
      "name": "Lock",
      "icon": "",
      "cterm_color": "250",
      "color": "#BBBBBB"
    },
    "kicad_sch": {
      "name": "KiCad",
      "icon": "",
      "cterm_color": "231",
      "color": "#FFFFFF"
    },
    "iso": {
      "name": "Iso",
      "icon": "",
      "cterm_color": "181",
      "color": "#D0BEC8"
    },
    "kts": {
      "name": "KotlinScript",
      "icon": "",
      "cterm_color": "99",
      "color": "#7F52FF"
    },
    "kt": {
      "name": "Kotlin",
      "icon": "",
      "cterm_color": "99",
      "color": "#7F52FF"
    },
    "log": {
      "name": "Log",
      "icon": "󰌱",
      "cterm_color": "253",
      "color": "#DDDDDD"
    },
    "kpp": {
      "name": "Krita",
      "icon": "",
      "cterm_color": "201",
      "color": "#F245FB"
    },
    "obj": {
      "name": "3DObjectFile",
      "icon": "󰆧",
      "cterm_color": "102",
      "color": "#888888"
    },
    "db": {
      "name": "Db",
      "icon": "",
      "cterm_color": "188",
      "color": "#DAD8D8"
    },
    "kicad_wks": {
      "name": "KiCad",
      "icon": "",
      "cterm_color": "231",
      "color": "#FFFFFF"
    },
    "kicad_pro": {
      "name": "KiCad",
      "icon": "",
      "cterm_color": "231",
      "color": "#FFFFFF"
    },
    "cow": {
      "name": "CowsayFile",
      "icon": "󰆚",
      "cterm_color": "130",
      "color": "#965824"
    },
    "dart": {
      "name": "Dart",
      "icon": "",
      "cterm_color": "25",
      "color": "#03589C"
    },
    "json": {
      "name": "Json",
      "icon": "",
      "cterm_color": "185",
      "color": "#CBCB41"
    },
    "ico": {
      "name": "Ico",
      "icon": "",
      "cterm_color": "185",
      "color": "#CBCB41"
    },
    "kicad_mod": {
      "name": "KiCad",
      "icon": "",
      "cterm_color": "231",
      "color": "#FFFFFF"
    },
    "kdb": {
      "name": "Kdb",
      "icon": "",
      "cterm_color": "71",
      "color": "#529B34"
    },
    "rlib": {
      "name": "Rlib",
      "icon": "",
      "cterm_color": "216",
      "color": "#DEA584"
    },
    "jxl": {
      "name": "JpegXl",
      "icon": "",
      "cterm_color": "140",
      "color": "#A074C4"
    },
    "fcparam": {
      "name": "FreeCAD",
      "icon": "",
      "cterm_color": "160",
      "color": "#CB333B"
    },
    "kicad_pcb": {
      "name": "KiCad",
      "icon": "",
      "cterm_color": "231",
      "color": "#FFFFFF"
    },
    "haml": {
      "name": "Haml",
      "icon": "",
      "cterm_color": "255",
      "color": "#EAEAE1"
    },
    "js": {
      "name": "Js",
      "icon": "",
      "cterm_color": "185",
      "color": "#CBCB41"
    },
    "jpg": {
      "name": "Jpg",
      "icon": "",
      "cterm_color": "140",
      "color": "#A074C4"
    },
    "jl": {
      "name": "Jl",
      "icon": "",
      "cterm_color": "133",
      "color": "#A270BA"
    },
    "ixx": {
      "name": "Ixx",
      "icon": "",
      "cterm_color": "74",
      "color": "#519ABA"
    },
    "ipynb": {
      "name": "Notebook",
      "icon": "",
      "cterm_color": "208",
      "color": "#F57D01"
    },
    "cfm": {
      "name": "ColdFusionTag",
      "icon": "",
      "cterm_color": "38",
      "color": "#01A4BA"
    },
    "3mf": {
      "name": "3DObjectFile",
      "icon": "󰆧",
      "cterm_color": "102",
      "color": "#888888"
    },
    "s": {
      "name": "ASM",
      "icon": "",
      "cterm_color": "25",
      "color": "#0071C5"
    },
    "hs": {
      "name": "Hs",
      "icon": "",
      "cterm_color": "140",
      "color": "#A074C4"
    },
    "fodt": {
      "name": "LibreOfficeWriter",
      "icon": "",
      "cterm_color": "81",
      "color": "#2DCBFD"
    },
    "odin": {
      "name": "Odin",
      "icon": "󰟢",
      "cterm_color": "32",
      "color": "#3882D2"
    },
    "cc": {
      "name": "CPlusPlus",
      "icon": "",
      "cterm_color": "204",
      "color": "#F34B7D"
    },
    "r": {
      "name": "R",
      "icon": "󰟔",
      "cterm_color": "25",
      "color": "#2266BA"
    },
    "srt": {
      "name": "Srt",
      "icon": "󰨖",
      "cterm_color": "214",
      "color": "#FFB713"
    },
    "rs": {
      "name": "Rs",
      "icon": "",
      "cterm_color": "216",
      "color": "#DEA584"
    },
    "html": {
      "name": "Html",
      "icon": "",
      "cterm_color": "196",
      "color": "#E44D26"
    },
    "icalendar": {
      "name": "Icalendar",
      "icon": "",
      "cterm_color": "18",
      "color": "#2B2E83"
    },
    "cson": {
      "name": "Cson",
      "icon": "",
      "cterm_color": "185",
      "color": "#CBCB41"
    },
    "x": {
      "name": "Logos",
      "icon": "",
      "cterm_color": "111",
      "color": "#599EFF"
    },
    "xslt": {
      "name": "Xslt",
      "icon": "󰗀",
      "cterm_color": "74",
      "color": "#33A9DC"
    },
    "ts": {
      "name": "TypeScript",
      "icon": "",
      "cterm_color": "74",
      "color": "#519ABA"
    },
    "cast": {
      "name": "Asciinema",
      "icon": "",
      "cterm_color": "208",
      "color": "#FD971F"
    },
    "csproj": {
      "name": "CSharpProject",
      "icon": "󰪮",
      "cterm_color": "56",
      "color": "#512BD4"
    },
    "hbs": {
      "name": "Hbs",
      "icon": "",
      "cterm_color": "202",
      "color": "#F0772B"
    },
    "gemspec": {
      "name": "Gemspec",
      "icon": "",
      "cterm_color": "52",
      "color": "#701516"
    },
    "sbt": {
      "name": "sbt",
      "icon": "",
      "cterm_color": "167",
      "color": "#CC3E44"
    },
    "cr": {
      "name": "Crystal",
      "icon": "",
      "cterm_color": "251",
      "color": "#C8C8C8"
    },
    "psb": {
      "name": "Psb",
      "icon": "",
      "cterm_color": "74",
      "color": "#519ABA"
    },
    "erl": {
      "name": "Erl",
      "icon": "",
      "cterm_color": "163",
      "color": "#B83998"
    },
    "ige": {
      "name": "Ige",
      "icon": "󰻫",
      "cterm_color": "101",
      "color": "#839463"
    },
    "gif": {
      "name": "Gif",
      "icon": "",
      "cterm_color": "140",
      "color": "#A074C4"
    },
    "gresource": {
      "name": "GTK",
      "icon": "",
      "cterm_color": "231",
      "color": "#FFFFFF"
    },
    "f3d": {
      "name": "Fusion360",
      "icon": "󰻫",
      "cterm_color": "101",
      "color": "#839463"
    },
    "fsscript": {
      "name": "Fsscript",
      "icon": "",
      "cterm_color": "74",
      "color": "#519ABA"
    },
    "cljd": {
      "name": "ClojureDart",
      "icon": "",
      "cterm_color": "74",
      "color": "#519ABA"
    },
    "dropbox": {
      "name": "Dropbox",
      "icon": "",
      "cterm_color": "27",
      "color": "#0061FE"
    },
    "txz": {
      "name": "Txz",
      "icon": "",
      "cterm_color": "214",
      "color": "#ECA517"
    },
    "info": {
      "name": "Info",
      "icon": "",
      "cterm_color": "230",
      "color": "#FFFFCD"
    },
    "fnl": {
      "name": "Fennel",
      "icon": "",
      "cterm_color": "230",
      "color": "#FFF3D7"
    },
    "d.ts": {
      "name": "TypeScriptDeclaration",
      "icon": "",
      "cterm_color": "172",
      "color": "#D59855"
    },
    "awk": {
      "name": "Awk",
      "icon": "",
      "cterm_color": "240",
      "color": "#4D5A5E"
    },
    "flc": {
      "name": "FIGletFontControl",
      "icon": "",
      "cterm_color": "255",
      "color": "#ECECEC"
    },
    "fdmdownload": {
      "name": "Fdmdownload",
      "icon": "",
      "cterm_color": "43",
      "color": "#44CDA8"
    },
    "json5": {
      "name": "Json5",
      "icon": "",
      "cterm_color": "185",
      "color": "#CBCB41"
    },
    "img": {
      "name": "Img",
      "icon": "",
      "cterm_color": "181",
      "color": "#D0BEC8"
    },
    "xlsx": {
      "name": "Xlsx",
      "icon": "󰈛",
      "cterm_color": "29",
      "color": "#207245"
    },
    "gd": {
      "name": "GDScript",
      "icon": "",
      "cterm_color": "66",
      "color": "#6D8086"
    },
    "htm": {
      "name": "Htm",
      "icon": "",
      "cterm_color": "196",
      "color": "#E34C26"
    },
    "glsl": {
      "name": "OpenGLShadingLanguage",
      "icon": "",
      "cterm_color": "67",
      "color": "#5586A6"
    },
    "epub": {
      "name": "Epub",
      "icon": "",
      "cterm_color": "215",
      "color": "#EAB16D"
    },
    "xls": {
      "name": "Xls",
      "icon": "󰈛",
      "cterm_color": "29",
      "color": "#207245"
    },
    "qss": {
      "name": "Qt",
      "icon": "",
      "cterm_color": "77",
      "color": "#40CD52"
    },
    "rss": {
      "name": "Rss",
      "icon": "",
      "cterm_color": "215",
      "color": "#FB9D3B"
    },
    "zst": {
      "name": "Zst",
      "icon": "",
      "cterm_color": "214",
      "color": "#ECA517"
    },
    "dockerignore": {
      "name": "DockerIgnore",
      "icon": "󰡨",
      "cterm_color": "68",
      "color": "#458EE6"
    },
    "edn": {
      "name": "Edn",
      "icon": "",
      "cterm_color": "74",
      "color": "#519ABA"
    },
    "m4a": {
      "name": "MPEG4",
      "icon": "",
      "cterm_color": "39",
      "color": "#00AFFF"
    },
    "adb": {
      "name": "AdaBody",
      "icon": "",
      "cterm_color": "111",
      "color": "#599EFF"
    },
    "flf": {
      "name": "FIGletFontFormat",
      "icon": "",
      "cterm_color": "255",
      "color": "#ECECEC"
    },
    "ini": {
      "name": "Ini",
      "icon": "",
      "cterm_color": "66",
      "color": "#6D8086"
    },
    "cue": {
      "name": "Cue",
      "icon": "󰲹",
      "cterm_color": "211",
      "color": "#ED95AE"
    },
    "conda": {
      "name": "Conda",
      "icon": "",
      "cterm_color": "34",
      "color": "#43B02A"
    },
    "css": {
      "name": "Css",
      "icon": "",
      "cterm_color": "91",
      "color": "#663399"
    },
    "blade.php": {
      "name": "Blade",
      "icon": "",
      "cterm_color": "203",
      "color": "#F05340"
    },
    "stories.ts": {
      "name": "StorybookTypeScript",
      "icon": "",
      "cterm_color": "204",
      "color": "#FF4785"
    },
    "godot": {
      "name": "GodotProject",
      "icon": "",
      "cterm_color": "66",
      "color": "#6D8086"
    },
    "fs": {
      "name": "Fs",
      "icon": "",
      "cterm_color": "74",
      "color": "#519ABA"
    },
    "ass": {
      "name": "Ass",
      "icon": "󰨖",
      "cterm_color": "214",
      "color": "#FFB713"
    },
    "graphql": {
      "name": "GraphQL",
      "icon": "",
      "cterm_color": "199",
      "color": "#E535AB"
    },
    "cmake": {
      "name": "CMake",
      "icon": "",
      "cterm_color": "254",
      "color": "#DCE3EB"
    }
  }
}
